MANIFEST.in
README.rst
UTILS.txt
setup.py
docs/HISTORY.txt
eea/__init__.py
eea.eggmonkey.egg-info/PKG-INFO
eea.eggmonkey.egg-info/SOURCES.txt
eea.eggmonkey.egg-info/dependency_links.txt
eea.eggmonkey.egg-info/entry_points.txt
eea.eggmonkey.egg-info/namespace_packages.txt
eea.eggmonkey.egg-info/not-zip-safe
eea.eggmonkey.egg-info/requires.txt
eea.eggmonkey.egg-info/top_level.txt
eea/eggmonkey/__init__.py
eea/eggmonkey/buildout.py
eea/eggmonkey/history.py
eea/eggmonkey/monkey.py
eea/eggmonkey/pypi.py
eea/eggmonkey/scm.py
eea/eggmonkey/tests.py
eea/eggmonkey/utils.py
eea/eggmonkey/version.py
eea/eggmonkey/version.txt
eea/eggmonkey/fixtures/1.txt
eea/eggmonkey/fixtures/2.txt